pythagore/__init__.py
pythagore/pythagore.py
pythagore-1.3.0.dist-info/licenses/LICENSE
pythagore-1.3.0.dist-info/METADATA
pythagore-1.3.0.dist-info/WHEEL
pythagore-1.3.0.dist-info/top_level.txt
pythagore-1.3.0.dist-info/RECORD
