Metadata-Version: 2.4
Name: pythagore
Version: 1.3.0
Summary: allows you to solve the Pythagorean theorem in Python
Home-page: https://github.com/Tina-1300/pythagore
Author: Tina
Author-email: tina.xytrfgthuji1348@gmail.com
License: MIT
Classifier: Programming Language :: Python :: 3
Classifier: License :: OSI Approved :: MIT License
Classifier: Operating System :: OS Independent
Classifier: Intended Audience :: Developers
Classifier: Topic :: Scientific/Engineering :: Mathematics
Requires-Python: >=3.13.0
License-File: LICENSE
Dynamic: license-file
